wecom/__init__.py
wecom/agent.py
wecom/base.py
wecom/callback.py
wecom/cli.py
wecom/contact.py
wecom/crypt.py
wecom/exception.py
wecom/external_contact.py
wecom/ierror.py
wecom/message.py
wecom/mixin.py
wecom/oa.py
wecom/oauth2.py
wecom/tx.py
wecom/clis/README.md
wecom/clis/__init__.py
wecom/clis/cli.py
wecom-2022.3.24.13.53.39.dist-info/AUTHORS.rst
wecom-2022.3.24.13.53.39.dist-info/LICENSE
wecom-2022.3.24.13.53.39.dist-info/METADATA
wecom-2022.3.24.13.53.39.dist-info/WHEEL
wecom-2022.3.24.13.53.39.dist-info/entry_points.txt
wecom-2022.3.24.13.53.39.dist-info/top_level.txt
wecom-2022.3.24.13.53.39.dist-info/RECORD
