Metadata-Version: 2.1
Name: wecom
Version: 2022.3.24.13.53.39
Summary: 企业微信SDK
Home-page: https://github.com/Jie-Yuan/wecom
Author: Betterme
Author-email: yuanjie@example.com
License: MIT license
Keywords: wecom
Platform: UNKNOWN
Classifier: Development Status :: 2 - Pre-Alpha
Classifier: Intended Audience :: Developers
Classifier: License :: OSI Approved :: MIT License
Classifier: Natural Language :: English
Classifier: Programming Language :: Python :: 3
Classifier: Programming Language :: Python :: 3.6
Classifier: Programming Language :: Python :: 3.7
Classifier: Programming Language :: Python :: 3.8
Requires-Python: >=3.6
License-File: LICENSE
License-File: AUTHORS.rst
Requires-Dist: meutils
Requires-Dist: xmltodict
Requires-Dist: pycryptodome
